HISTORY.md
LICENSE.txt
README.md
pyproject.toml
setup.py
src/invesytoolbox/__init__.py
src/invesytoolbox/itb_data.py
src/invesytoolbox/itb_date_time.py
src/invesytoolbox/itb_email_phone.py
src/invesytoolbox/itb_html.py
src/invesytoolbox/itb_locales.py
src/invesytoolbox/itb_restricted_python.py
src/invesytoolbox/itb_security.py
src/invesytoolbox/itb_text_name.py
src/invesytoolbox/itb_www.py
src/invesytoolbox.egg-info/PKG-INFO
src/invesytoolbox.egg-info/SOURCES.txt
src/invesytoolbox.egg-info/dependency_links.txt
src/invesytoolbox.egg-info/requires.txt
src/invesytoolbox.egg-info/top_level.txt
src/tests/__init__.py
src/tests/test_data.py
src/tests/test_date_time.py
src/tests/test_email_phone.py
src/tests/test_html.py
src/tests/test_locales.py
src/tests/test_text_name.py
src/tests/test_www.py