Metadata-Version: 2.4
Name: invesytoolbox
Version: 0.0.26
Summary: Tools for Python scripts or terminal
Author-email: Georg Pfolz <georg.pfolz@invesy.at>
Project-URL: Homepage, https://gitlab.com/Rastaf/invesytoolbox
Project-URL: Issue Tracker, https://gitlab.com/Rastaf/invesytoolbox/issues
Project-URL: Source Code, https://gitlab.com/Rastaf/invesytoolbox.git
Project-URL: Changelog, https://gitlab.com/Rastaf/invesytoolbox/blob/main/HISTORY.md
Project-URL: Documentation, https://rastaf.gitlab.io/invesytoolbox/
Keywords: toolbox,utilities,scripts,terminal
Classifier: Programming Language :: Python :: 3
Classifier: Programming Language :: Python :: 3.7
Classifier: Programming Language :: Python :: 3.8
Classifier: Programming Language :: Python :: 3.9
Classifier: Programming Language :: Python :: 3.10
Classifier: Programming Language :: Python :: 3.11
Classifier: Operating System :: OS Independent
Requires-Python: <3.12,>=3.7
License-File: LICENSE.txt
Requires-Dist: beautifulsoup4
Requires-Dist: babel
Requires-Dist: colorama
Requires-Dist: DateTime
Requires-Dist: gender_guesser
Requires-Dist: holidays>0.13
Requires-Dist: nameparser
Requires-Dist: phonenumbers
Requires-Dist: pycountry
Requires-Dist: unidecode
Requires-Dist: vobject
Dynamic: license-file
